textual_kitty/__init__.py
textual_kitty/__main__.py
textual_kitty/demo.py
textual_kitty/geometry.py
textual_kitty/pixeldata.py
textual_kitty/terminal.py
textual_kitty/utils.py
textual_kitty-0.4.0.dist-info/METADATA
textual_kitty-0.4.0.dist-info/WHEEL
textual_kitty-0.4.0.dist-info/top_level.txt
textual_kitty-0.4.0.dist-info/RECORD
