Metadata-Version: 2.1
Name: textual-kitty
Version: 0.4.0
Summary: Render images via Kitty's Terminal Graphics Protocol with Rich and Textual
Author-email: Simon Hayessen <simon@lnqs.io>
Project-URL: Homepage, https://github.com/lnqs/textual-kitty
Project-URL: Documentation, https://github.com/lnqs/textual-kitty
Project-URL: Repository, https://github.com/lnqs/textual-kitty
Project-URL: Issues, https://github.com/lnqs/textual-kitty/issues
Classifier: Development Status :: 4 - Beta
Classifier: Intended Audience :: Developers
Classifier: Topic :: Software Development :: Libraries
Classifier: Topic :: Software Development :: User Interfaces
Classifier: License :: OSI Approved :: GNU General Public License (GPL)
Classifier: License :: OSI Approved :: GNU General Public License v3 or later (GPLv3+)
Classifier: Programming Language :: Python :: 3
Classifier: Programming Language :: Python :: 3.10
Classifier: Programming Language :: Python :: 3.11
Classifier: Programming Language :: Python :: 3.12
Requires-Dist: pillow>=10.4.0
Requires-Dist: rich>=13.8.0
Provides-Extra: dev
Requires-Dist: mypy; extra == "dev"
Requires-Dist: pytest; extra == "dev"
Requires-Dist: pytest-asyncio; extra == "dev"
Requires-Dist: pytest-cov; extra == "dev"
Requires-Dist: ruff; extra == "dev"
Requires-Dist: syrupy; extra == "dev"
Requires-Dist: textual-dev; extra == "dev"
Provides-Extra: textual
Requires-Dist: textual>=0.81.0; extra == "textual"
